[{"id":"bitcoin","symbol":"btc","name":"Bitcoin","image":"https://assets.coingecko.com/coins/images/1/large/bitcoin.png?1547033579","current_price":30591,"market_cap":582361331790,"market_cap_rank":1,"fully_diluted_valuation":642419341750,"total_volume":45184022974,"high_24h":32293,"low_24h":30409,"price_change_24h":-1678.725211134948,"price_change_percentage_24h":-5.2021,"market_cap_change_24h":-31038641036.582886,"market_cap_change_percentage_24h":-5.0601,"circulating_supply":19036768.0,"total_supply":21000000.0,"max_supply":21000000.0,"ath":69045,"ath_change_percentage":-55.57209,"ath_date":"2021-11-10T14:24:11.849Z","atl":67.81,"atl_change_percentage":45137.57604,"atl_date":"2013-07-06T00:00:00.000Z","roi":null,"last_updated":"2022-05-11T07:00:23.378Z"},{"id":"ethereum","symbol":"eth","name":"Ethereum","image":"https://assets.coingecko.com/coins/images/279/large/ethereum.png?1595348880","current_price":2304.48,"market_cap":278224548839,"market_cap_rank":2,"fully_diluted_valuation":null,"total_volume":31007703321,"high_24h":2453.6,"low_24h":2271.02,"price_change_24h":-105.0118924481153,"price_change_percentage_24h":-4.35825,"market_cap_change_24h":-12607215755.77716,"market_cap_change_percentage_24h":-4.33488,"circulating_supply":120731820.4365,"total_supply":null,"max_supply":null,"ath":4878.26,"ath_change_percentage":-52.6189,"ath_date":"2021-11-10T14:24:19.604Z","atl":0.432979,"atl_change_percentage":533730.51499,"atl_date":"2015-10-20T00:00:00.000Z","roi":{"times":99.6793636924881,"currency":"btc","percentage":9967.93636924881},"last_updated":"2022-05-11T07:00:25.959Z"},{"id":"tether","symbol":"usdt","name":"Tether","image":"https://assets.coingecko.com/coins/images/325/large/Tether-logo.png?1598003707","current_price":1.002,"market_cap":82990558997,"market_cap_rank":3,"fully_diluted_valuation":null,"total_volume":94810787073,"high_24h":1.01,"low_24h":0.99474,"price_change_24h":-0.00053842639790691,"price_change_percentage_24h":-0.05369,"market_cap_change_24h":-102346240.94314575,"market_cap_change_percentage_24h":-0.12317,"circulating_supply":83147694182.5932,"total_supply":83147694182.5932,"max_supply":null,"ath":1.32,"ath_change_percentage":-24.56249,"ath_date":"2018-07-24T00:00:00.000Z","atl":0.572521,"atl_change_percentage":74.33599,"atl_date":"2015-03-02T00:00:00.000Z","roi":null,"last_updated":"2022-05-11T07:02:48.033Z"},{"id":"binancecoin","symbol":"bnb","name":"BNB","image":"https://assets.coingecko.com/coins/images/825/large/bnb-icon2_2x.png?1644979850","current_price":303.27,"market_cap":50990715021,"market_cap_rank":4,"fully_diluted_valuation":50990715021,"total_volume":3698102563,"high_24h":330.52,"low_24h":304.07,"price_change_24h":-24.799053817208062,"price_change_percentage_24h":-7.55912,"market_cap_change_24h":-4275852294.361351,"market_cap_change_percentage_24h":-7.73678,"circulating_supply":168137035.9,"total_supply":168137035.9,"max_supply":168137035.9,"ath":686.31,"ath_change_percentage":-55.69437,"ath_date":"2021-05-10T07:24:17.097Z","atl":0.0398177,"atl_change_percentage":763561.55415,"atl_date":"2017-10-19T00:00:00.000Z","roi":null,"last_updated":"2022-05-11T07:01:02.274Z"},{"id":"usd-coin","symbol":"usdc","name":"USD Coin","image":"https://assets.coingecko.com/coins/images/6319/large/USD_Coin_icon.png?1547042389","current_price":1.003,"market_cap":48358959759,"market_cap_rank":5,"fully_diluted_valuation":null,"total_volume":8542353384,"high_24h":1.008,"low_24h":0.992509,"price_change_24h":0.00231869,"price_change_percentage_24h":0.23175,"market_cap_change_24h":-138317624.74020386,"market_cap_change_percentage_24h":-0.28521,"circulating_supply":48359585114.2826,"total_supply":48368339181.4943,"max_supply":null,"ath":1.17,"ath_change_percentage":-14.72824,"ath_date":"2019-05-08T00:40:28.300Z","atl":0.891848,"atl_change_percentage":12.12529,"atl_date":"2021-05-19T13:14:05.611Z","roi":null,"last_updated":"2022-05-11T07:02:12.057Z"},{"id":"ripple","symbol":"xrp","name":"XRP","image":"https://assets.coingecko.com/coins/images/44/large/xrp-symbol-white-128.png?1605778731","current_price":0.502362,"market_cap":24285732725,"market_cap_rank":6,"fully_diluted_valuation":50236191149,"total_volume":3540364267,"high_24h":0.537258,"low_24h":0.499793,"price_change_24h":-0.02787261123207685,"price_change_percentage_24h":-5.25666,"market_cap_change_24h":-1315453733.838211,"market_cap_change_percentage_24h":-5.13825,"circulating_supply":48343101197.0,"total_supply":100000000000.0,"max_supply":100000000000.0,"ath":3.4,"ath_change_percentage":-85.19068,"ath_date":"2018-01-07T00:00:00.000Z","atl":0.00268621,"atl_change_percentage":18635.98575,"atl_date":"2014-05-22T00:00:00.000Z","roi":null,"last_updated":"2022-05-11T07:00:56.266Z"},{"id":"solana","symbol":"sol","name":"Solana","image":"https://assets.coingecko.com/coins/images/4128/large/solana.png?1640133422","current_price":62.34,"market_cap":21019201901,"market_cap_rank":7,"fully_diluted_valuation":null,"total_volume":2572699550,"high_24h":73.7,"low_24h":62.41,"price_change_24h":-8.938369589070376,"price_change_percentage_24h":-12.53986,"market_cap_change_24h":-3027379332.783783,"market_cap_change_percentage_24h":-12.58965,"circulating_supply":336790590.961182,"total_supply":508180963.57,"max_supply":null,"ath":259.96,"ath_change_percentage":-75.99225,"ath_date":"2021-11-06T21:54:35.825Z","atl":0.500801,"atl_change_percentage":12362.10245,"atl_date":"2020-05-11T19:35:23.449Z","roi":null,"last_updated":"2022-05-11T07:02:52.608Z"},{"id":"cardano","symbol":"ada","name":"Cardano","image":"https://assets.coingecko.com/coins/images/975/large/cardano.png?1547034860","current_price":0.607533,"market_cap":20578075482,"market_cap_rank":8,"fully_diluted_valuation":27380431937,"total_volume":1612411276,"high_24h":0.694441,"low_24h":0.608454,"price_change_24h":-0.07913924674903339,"price_change_percentage_24h":-11.52504,"market_cap_change_24h":-2716287452.1745605,"market_cap_change_percentage_24h":-11.66071,"circulating_supply":33820262543.95,"total_supply":45000000000.0,"max_supply":45000000000.0,"ath":3.09,"ath_change_percentage":-80.28923,"ath_date":"2021-09-02T06:00:10.474Z","atl":0.01925275,"atl_change_percentage":3060.34925,"atl_date":"2020-03-13T02:22:55.044Z","roi":null,"last_updated":"2022-05-11T07:02:07.021Z"},{"id":"binance-usd","symbol":"busd","name":"Binance USD","image":"https://assets.coingecko.com/coins/images/9576/large/BUSD.png?1568947766","current_price":0.985309,"market_cap":16876946880,"market_cap_rank":9,"fully_diluted_valuation":null,"total_volume":8098763868,"high_24h":1.015,"low_24h":0.977324,"price_change_24h":-0.013642760342250315,"price_change_percentage_24h":-1.36571,"market_cap_change_24h":-386824803.55509377,"market_cap_change_percentage_24h":-2.24067,"circulating_supply":17128587263.63,"total_supply":17128587263.63,"max_supply":null,"ath":1.15,"ath_change_percentage":-14.63305,"ath_date":"2020-03-13T02:35:42.953Z","atl":0.901127,"atl_change_percentage":9.3418,"atl_date":"2021-05-19T13:04:37.445Z","roi":null,"last_updated":"2022-05-11T07:00:58.861Z"},{"id":"dogecoin","symbol":"doge","name":"Dogecoin","image":"https://assets.coingecko.com/coins/images/5/large/dogecoin.png?1547792256","current_price":0.104022,"market_cap":13815658151,"market_cap_rank":10,"fully_diluted_valuation":null,"total_volume":1159769730,"high_24h":0.117506,"low_24h":0.104135,"price_change_24h":-0.01013767489769174,"price_change_percentage_24h":-8.88024,"market_cap_change_24h":-1339322590.9350338,"market_cap_change_percentage_24h":-8.83751,"circulating_supply":132670764299.894,"total_supply":null,"max_supply":null,"ath":0.731578,"ath_change_percentage":-85.76572,"ath_date":"2021-05-08T05:08:23.458Z","atl":8.69e-05,"atl_change_percentage":119727.85745,"atl_date":"2015-05-06T00:00:00.000Z","roi":null,"last_updated":"2022-05-11T07:02:12.148Z"},{"id":"polkadot","symbol":"dot","name":"Polkadot","image":"https://assets.coingecko.com/coins/images/12171/large/polkadot.png?1639712644","current_price":10.58,"market_cap":11753216309,"market_cap_rank":11,"fully_diluted_valuation":null,"total_volume":1130603899,"high_24h":12.27,"low_24h":10.59,"price_change_24h":-1.4474140826389998,"price_change_percentage_24h":-12.0298,"market_cap_change_24h":-1697382408.7279682,"market_cap_change_percentage_24h":-12.61938,"circulating_supply":1110418772.95364,"total_supply":1191367230.75496,"max_supply":null,"ath":54.98,"ath_change_percentage":-80.74812,"ath_date":"2021-11-04T14:10:09.301Z","atl":2.7,"atl_change_percentage":292.40161,"atl_date":"2020-08-20T05:48:11.359Z","roi":null,"last_updated":"2022-05-11T07:01:30.338Z"},{"id":"avalanche-2","symbol":"avax","name":"Avalanche","image":"https://assets.coingecko.com/coins/images/12559/large/coin-round-red.png?1604021818","current_price":37.85,"market_cap":10213724859,"market_cap_rank":12,"fully_diluted_valuation":27341352082,"total_volume":1280691495,"high_24h":49.67,"low_24h":37.97,"price_change_24h":-10.136851687462766,"price_change_percentage_24h":-21.12387,"market_cap_change_24h":-2702992013.9657726,"market_cap_change_percentage_24h":-20.92631,"circulating_supply":268965553.578082,"total_supply":377752194.4695483,"max_supply":720000000.0,"ath":144.96,"ath_change_percentage":-73.88939,"ath_date":"2021-11-21T14:18:56.538Z","atl":2.8,"atl_change_percentage":1251.28137,"atl_date":"2020-12-31T13:15:21.540Z","roi":null,"last_updated":"2022-05-11T07:01:41.632Z"},{"id":"staked-ether","symbol":"steth","name":"Lido Staked Ether","image":"https://assets.coingecko.com/coins/images/13442/large/steth_logo.png?1608607546","current_price":2283.84,"market_cap":9618679107,"market_cap_rank":14,"fully_diluted_valuation":9618679107,"total_volume":68924216,"high_24h":2440.23,"low_24h":2256.67,"price_change_24h":-114.98975342705671,"price_change_percentage_24h":-4.79358,"market_cap_change_24h":-391645738.3482933,"market_cap_change_percentage_24h":-3.91242,"circulating_supply":4161139.30058161,"total_supply":4161139.30058161,"max_supply":4161139.30058161,"ath":4829.57,"ath_change_percentage":-52.71132,"ath_date":"2021-11-10T14:40:47.256Z","atl":482.9,"atl_change_percentage":372.94638,"atl_date":"2020-12-22T04:08:21.854Z","roi":null,"last_updated":"2022-05-11T07:02:25.021Z"},{"id":"wrapped-bitcoin","symbol":"wbtc","name":"Wrapped Bitcoin","image":"https://assets.coingecko.com/coins/images/7598/large/wrapped_bitcoin_wbtc.png?1548822744","current_price":30705,"market_cap":8722192473,"market_cap_rank":15,"fully_diluted_valuation":8722192473,"total_volume":498312684,"high_24h":32348,"low_24h":30397,"price_change_24h":-1526.3257686183752,"price_change_percentage_24h":-4.73557,"market_cap_change_24h":-465533921.50725746,"market_cap_change_percentage_24h":-5.06691,"circulating_supply":284204.94000022,"total_supply":284204.94000022,"max_supply":284204.94000022,"ath":70643,"ath_change_percentage":-56.55674,"ath_date":"2021-11-10T14:40:19.650Z","atl":3139.17,"atl_change_percentage":877.63954,"atl_date":"2019-04-02T00:00:00.000Z","roi":null,"last_updated":"2022-05-11T07:02:00.741Z"},{"id":"terrausd","symbol":"ust","name":"TerraUSD","image":"https://assets.coingecko.com/coins/images/12681/large/UST.png?1601612407","current_price":0.520728,"market_cap":8646539359,"market_cap_rank":13,"fully_diluted_valuation":null,"total_volume":1467070535,"high_24h":0.934019,"low_24h":0.538159,"price_change_24h":-0.40993399860641033,"price_change_percentage_24h":-44.04757,"market_cap_change_24h":-8282135241.978931,"market_cap_change_percentage_24h":-48.92371,"circulating_supply":16604715701.4249,"total_supply":16736502621.1871,"max_supply":null,"ath":1.092,"ath_change_percentage":-52.31023,"ath_date":"2021-01-11T22:30:57.984Z","atl":0.538159,"atl_change_percentage":-3.23897,"atl_date":"2022-05-11T06:58:40.796Z","roi":null,"last_updated":"2022-05-11T07:00:24.580Z"},{"id":"shiba-inu","symbol":"shib","name":"Shiba Inu","image":"https://assets.coingecko.com/coins/images/11939/large/shiba.png?1622619446","current_price":1.513e-05,"market_cap":8330305314,"market_cap_rank":16,"fully_diluted_valuation":null,"total_volume":1529548396,"high_24h":1.784e-05,"low_24h":1.522e-05,"price_change_24h":-1.856950098585e-06,"price_change_percentage_24h":-10.93133,"market_cap_change_24h":-1026518647.0125895,"market_cap_change_percentage_24h":-10.9708,"circulating_supply":549146987315505.4,"total_supply":1.0e+15,"max_supply":null,"ath":8.616e-05,"ath_change_percentage":-82.39352,"ath_date":"2021-10-28T03:54:55.568Z","atl":5.6366e-11,"atl_change_percentage":26912266.6339,"atl_date":"2020-11-28T11:26:25.838Z","roi":null,"last_updated":"2022-05-11T07:02:33.724Z"},{"id":"tron","symbol":"trx","name":"TRON","image":"https://assets.coingecko.com/coins/images/1094/large/tron-logo.png?1547035066","current_price":0.075573,"market_cap":7420832006,"market_cap_rank":17,"fully_diluted_valuation":null,"total_volume":2314875509,"high_24h":0.082081,"low_24h":0.074419,"price_change_24h":-0.005233146772091733,"price_change_percentage_24h":-6.47619,"market_cap_change_24h":-547713989.4251966,"market_cap_change_percentage_24h":-6.87345,"circulating_supply":98194531912.195,"total_supply":101900409184.273,"max_supply":null,"ath":0.231673,"ath_change_percentage":-67.37952,"ath_date":"2018-01-05T00:00:00.000Z","atl":0.00180434,"atl_change_percentage":4088.38432,"atl_date":"2017-11-12T00:00:00.000Z","roi":{"times":38.77513798022485,"currency":"usd","percentage":3877.513798022485},"last_updated":"2022-05-11T07:00:12.784Z"},{"id":"dai","symbol":"dai","name":"Dai","image":"https://assets.coingecko.com/coins/images/9956/large/4943.png?1636636734","current_price":1.002,"market_cap":6931207446,"market_cap_rank":18,"fully_diluted_valuation":6931207446,"total_volume":628515135,"high_24h":1.009,"low_24h":0.994962,"price_change_24h":0.00074032,"price_change_percentage_24h":0.07395,"market_cap_change_24h":-148272698.22274876,"market_cap_change_percentage_24h":-2.0944,"circulating_supply":6943014079.49711,"total_supply":6943014079.49711,"max_supply":6943014079.49711,"ath":1.22,"ath_change_percentage":-18.10037,"ath_date":"2020-03-13T03:02:50.373Z","atl":0.903243,"atl_change_percentage":10.5239,"atl_date":"2019-11-25T00:04:18.137Z","roi":null,"last_updated":"2022-05-11T07:02:34.684Z"},{"id":"near","symbol":"near","name":"NEAR Protocol","image":"https://assets.coingecko.com/coins/images/10365/large/near_icon.png?1601359077","current_price":8.47,"market_cap":5780291092,"market_cap_rank":19,"fully_diluted_valuation":8479752375,"total_volume":1156564364,"high_24h":10.65,"low_24h":8.48,"price_change_24h":-2.101049519650136,"price_change_percentage_24h":-19.88277,"market_cap_change_24h":-1430440771.4158802,"market_cap_change_percentage_24h":-19.83766,"circulating_supply":681658005.659806,"total_supply":1000000000.0,"max_supply":1000000000.0,"ath":20.44,"ath_change_percentage":-58.51012,"ath_date":"2022-01-16T22:09:45.873Z","atl":0.526762,"atl_change_percentage":1509.78677,"atl_date":"2020-11-04T16:09:15.137Z","roi":null,"last_updated":"2022-05-11T07:02:45.152Z"},{"id":"matic-network","symbol":"matic","name":"Polygon","image":"https://assets.coingecko.com/coins/images/4713/large/matic-token-icon.png?1624446912","current_price":0.833169,"market_cap":5733925934,"market_cap_rank":20,"fully_diluted_valuation":8342816191,"total_volume":1199066637,"high_24h":0.977862,"low_24h":0.834282,"price_change_24h":-0.11882084099134327,"price_change_percentage_24h":-12.48131,"market_cap_change_24h":-810086313.2546701,"market_cap_change_percentage_24h":-12.37905,"circulating_supply":6872890164.27,"total_supply":10000000000.0,"max_supply":10000000000.0,"ath":2.92,"ath_change_percentage":-71.39212,"ath_date":"2021-12-27T02:08:34.307Z","atl":0.00314376,"atl_change_percentage":26437.67554,"atl_date":"2019-05-10T00:00:00.000Z","roi":{"times":315.7943847204633,"currency":"usd","percentage":31579.43847204633},"last_updated":"2022-05-11T07:01:58.315Z"},{"id":"crypto-com-chain","symbol":"cro","name":"Cronos","image":"https://assets.coingecko.com/coins/images/7310/large/oCw2s3GI_400x400.jpeg?1645172042","current_price":0.226963,"market_cap":5732654123,"market_cap_rank":21,"fully_diluted_valuation":null,"total_volume":87711548,"high_24h":0.240718,"low_24h":0.22549,"price_change_24h":-0.008098815886023765,"price_change_percentage_24h":-3.4454,"market_cap_change_24h":-189566058.00321388,"market_cap_change_percentage_24h":-3.20093,"circulating_supply":25263013692.0,"total_supply":30263013692.0,"max_supply":null,"ath":0.965407,"ath_change_percentage":-76.49501,"ath_date":"2021-11-24T15:53:54.855Z","atl":0.0121196,"atl_change_percentage":1772.32993,"atl_date":"2019-02-08T00:00:00.000Z","roi":null,"last_updated":"2022-05-11T07:01:37.240Z"},{"id":"litecoin","symbol":"ltc","name":"Litecoin","image":"https://assets.coingecko.com/coins/images/2/large/litecoin.png?1547033580","current_price":76.64,"market_cap":5391337107,"market_cap_rank":22,"fully_diluted_valuation":6445643242,"total_volume":1216895374,"high_24h":84.57,"low_24h":76.73,"price_change_24h":-6.368051665970185,"price_change_percentage_24h":-7.672,"market_cap_change_24h":-444610449.4806013,"market_cap_change_percentage_24h":-7.61848,"circulating_supply":70260220.7334713,"total_supply":84000000.0,"max_supply":84000000.0,"ath":410.26,"ath_change_percentage":-81.29642,"ath_date":"2021-05-10T03:13:07.904Z","atl":1.15,"atl_change_percentage":6579.18187,"atl_date":"2015-01-14T00:00:00.000Z","roi":null,"last_updated":"2022-05-11T07:01:01.211Z"},{"id":"leo-token","symbol":"leo","name":"LEO Token","image":"https://assets.coingecko.com/coins/images/8418/large/leo-token.png?1558326215","current_price":5.43,"market_cap":5086664457,"market_cap_rank":23,"fully_diluted_valuation":null,"total_volume":2595631,"high_24h":5.52,"low_24h":5.09,"price_change_24h":0.306285,"price_change_percentage_24h":5.9786,"market_cap_change_24h":289242359,"market_cap_change_percentage_24h":6.02912,"circulating_supply":936168597.9,"total_supply":985239504.0,"max_supply":null,"ath":8.14,"ath_change_percentage":-33.21128,"ath_date":"2022-02-08T17:40:10.285Z","atl":0.799859,"atl_change_percentage":579.30606,"atl_date":"2019-12-24T15:14:35.376Z","roi":null,"last_updated":"2022-05-11T07:02:24.989Z"},{"id":"ftx-token","symbol":"ftt","name":"FTX Token","image":"https://assets.coingecko.com/coins/images/9026/large/F.png?1609051564","current_price":31.8,"market_cap":4345142412,"market_cap_rank":24,"fully_diluted_valuation":10578387917,"total_volume":148292525,"high_24h":34.73,"low_24h":31.82,"price_change_24h":-2.5035424775326973,"price_change_percentage_24h":-7.29823,"market_cap_change_24h":-350333577.56151485,"market_cap_change_percentage_24h":-7.46109,"circulating_supply":136538847.81874323,"total_supply":332408183.885971,"max_supply":332408183.885971,"ath":84.18,"ath_change_percentage":-62.1965,"ath_date":"2021-09-09T16:59:43.151Z","atl":1.15,"atl_change_percentage":2667.97545,"atl_date":"2019-09-06T00:00:00.000Z","roi":null,"last_updated":"2022-05-11T07:02:02.069Z"},{"id":"bitcoin-cash","symbol":"bch","name":"Bitcoin Cash","image":"https://assets.coingecko.com/coins/images/780/large/bitcoin-cash-circle.png?1594689492","current_price":221.78,"market_cap":4227114772,"market_cap_rank":25,"fully_diluted_valuation":4657291941,"total_volume":573407576,"high_24h":242.93,"low_24h":222.09,"price_change_24h":-20.34379874400338,"price_change_percentage_24h":-8.40238,"market_cap_change_24h":-387515399.393579,"market_cap_change_percentage_24h":-8.39754,"circulating_supply":19060306.1466512,"total_supply":21000000.0,"max_supply":21000000.0,"ath":3785.82,"ath_change_percentage":-94.12501,"ath_date":"2017-12-20T00:00:00.000Z","atl":76.93,"atl_change_percentage":189.09733,"atl_date":"2018-12-16T00:00:00.000Z","roi":null,"last_updated":"2022-05-11T07:00:25.054Z"},{"id":"chainlink","symbol":"link","name":"Chainlink","image":"https://assets.coingecko.com/coins/images/877/large/chainlink-new-logo.png?1547034700","current_price":8.16,"market_cap":3812269310,"market_cap_rank":26,"fully_diluted_valuation":8163150655,"total_volume":885087582,"high_24h":9.3,"low_24h":8.26,"price_change_24h":-0.875297783986861,"price_change_percentage_24h":-9.68416,"market_cap_change_24h":-408903463.89358234,"market_cap_change_percentage_24h":-9.68696,"circulating_supply":467009549.5205637,"total_supply":1000000000.0,"max_supply":1000000000.0,"ath":52.7,"ath_change_percentage":-84.50909,"ath_date":"2021-05-10T00:13:57.214Z","atl":0.148183,"atl_change_percentage":5408.84544,"atl_date":"2017-11-29T00:00:00.000Z","roi":null,"last_updated":"2022-05-11T07:00:09.425Z"},{"id":"algorand","symbol":"algo","name":"Algorand","image":"https://assets.coingecko.com/coins/images/4380/large/download.png?1547039725","current_price":0.551519,"market_cap":3757817446,"market_cap_rank":27,"fully_diluted_valuation":5516899278,"total_volume":362970903,"high_24h":0.658066,"low_24h":0.55169,"price_change_24h":-0.08951288092661569,"price_change_percentage_24h":-13.96386,"market_cap_change_24h":-610142619.9292836,"market_cap_change_percentage_24h":-13.96859,"circulating_supply":6811466470.38602,"total_supply":7219371791.52067,"max_supply":10000000000.0,"ath":3.56,"ath_change_percentage":-84.50811,"ath_date":"2019-06-20T14:51:19.480Z","atl":0.105336,"atl_change_percentage":423.74544,"atl_date":"2020-03-13T02:20:48.438Z","roi":{"times":-0.7702002363916521,"currency":"usd","percentage":-77.02002363916522},"last_updated":"2022-05-11T07:02:22.069Z"},{"id":"okb","symbol":"okb","name":"OKB","image":"https://assets.coingecko.com/coins/images/4463/large/WeChat_Image_20220118095654.png?1642471050","current_price":14.23,"market_cap":3684446802,"market_cap_rank":29,"fully_diluted_valuation":null,"total_volume":71782107,"high_24h":15.11,"low_24h":14.16,"price_change_24h":-0.8245352443068938,"price_change_percentage_24h":-5.4783,"market_cap_change_24h":-224949601.78465748,"market_cap_change_percentage_24h":-5.75408,"circulating_supply":260143733.83,"total_supply":300000000.0,"max_supply":null,"ath":44.01,"ath_change_percentage":-67.81497,"ath_date":"2021-05-03T01:03:16.108Z","atl":0.580608,"atl_change_percentage":2339.36006,"atl_date":"2019-01-14T00:00:00.000Z","roi":null,"last_updated":"2022-05-11T07:01:37.250Z"},{"id":"cosmos","symbol":"atom","name":"Cosmos Hub","image":"https://assets.coingecko.com/coins/images/1481/large/cosmos_hub.png?1555657960","current_price":12.33,"market_cap":3609862016,"market_cap_rank":28,"fully_diluted_valuation":null,"total_volume":866877906,"high_24h":15.04,"low_24h":12.34,"price_change_24h":-2.595356691073695,"price_change_percentage_24h":-17.38659,"market_cap_change_24h":-781747845.1525321,"market_cap_change_percentage_24h":-17.80094,"circulating_supply":292586163.827428,"total_supply":null,"max_supply":null,"ath":44.45,"ath_change_percentage":-72.24206,"ath_date":"2022-01-17T00:34:41.497Z","atl":1.16,"atl_change_percentage":963.55433,"atl_date":"2020-03-13T02:27:44.591Z","roi":{"times":122.3199272761386,"currency":"usd","percentage":12231.99272761386},"last_updated":"2022-05-11T07:02:44.729Z"},{"id":"stellar","symbol":"xlm","name":"Stellar","image":"https://assets.coingecko.com/coins/images/100/large/Stellar_symbol_black_RGB.png?1552356157","current_price":0.142609,"market_cap":3537869304,"market_cap_rank":30,"fully_diluted_valuation":7130036495,"total_volume":375617007,"high_24h":0.155711,"low_24h":0.142596,"price_change_24h":-0.012238626303352427,"price_change_percentage_24h":-7.90368,"market_cap_change_24h":-298171461.1876445,"market_cap_change_percentage_24h":-7.7729,"circulating_supply":24810502785.5832,"total_supply":50001787831.5006,"max_supply":50001787831.5006,"ath":0.875563,"ath_change_percentage":-83.71384,"ath_date":"2018-01-03T00:00:00.000Z","atl":0.00047612,"atl_change_percentage":29849.30171,"atl_date":"2015-03-05T00:00:00.000Z","roi":null,"last_updated":"2022-05-11T07:01:37.454Z"},{"id":"ethereum-classic","symbol":"etc","name":"Ethereum Classic","image":"https://assets.coingecko.com/coins/images/453/large/ethereum-classic-logo.png?1547034169","current_price":22.98,"market_cap":3101941368,"market_cap_rank":32,"fully_diluted_valuation":4851704511,"total_volume":492337935,"high_24h":25.5,"low_24h":23.03,"price_change_24h":-2.1984894740796257,"price_change_percentage_24h":-8.73111,"market_cap_change_24h":-290700380.642015,"market_cap_change_percentage_24h":-8.56856,"circulating_supply":134711222.572916,"total_supply":210700000.0,"max_supply":210700000.0,"ath":167.09,"ath_change_percentage":-86.21866,"ath_date":"2021-05-06T18:34:22.133Z","atl":0.615038,"atl_change_percentage":3643.93119,"atl_date":"2016-07-25T00:00:00.000Z","roi":{"times":50.06992163998487,"currency":"usd","percentage":5006.992163998487},"last_updated":"2022-05-11T07:02:10.575Z"},{"id":"terra-luna","symbol":"luna","name":"Terra","image":"https://assets.coingecko.com/coins/images/8284/large/luna1557227471663.png?1567147072","current_price":6.57,"market_cap":2924351961,"market_cap_rank":31,"fully_diluted_valuation":6701324579,"total_volume":10034239989,"high_24h":35.0,"low_24h":6.7,"price_change_24h":-28.232235765636563,"price_change_percentage_24h":-81.12004,"market_cap_change_24h":-9682991670.65688,"market_cap_change_percentage_24h":-76.80438,"circulating_supply":436384169.406032,"total_supply":823021830.283685,"max_supply":1000000000.0,"ath":119.18,"ath_change_percentage":-94.37715,"ath_date":"2022-04-05T12:24:58.854Z","atl":0.121798,"atl_change_percentage":5401.99147,"atl_date":"2020-03-18T17:03:01.083Z","roi":null,"last_updated":"2022-05-11T07:02:44.712Z"},{"id":"monero","symbol":"xmr","name":"Monero","image":"https://assets.coingecko.com/coins/images/69/large/monero_logo.png?1547033729","current_price":152.8,"market_cap":2768439591,"market_cap_rank":33,"fully_diluted_valuation":null,"total_volume":253121419,"high_24h":187.82,"low_24h":152.79,"price_change_24h":-33.40448829778131,"price_change_percentage_24h":-17.93972,"market_cap_change_24h":-613201735.7865763,"market_cap_change_percentage_24h":-18.13326,"circulating_supply":18119523.9675957,"total_supply":null,"max_supply":null,"ath":542.33,"ath_change_percentage":-71.82731,"ath_date":"2018-01-09T00:00:00.000Z","atl":0.216177,"atl_change_percentage":70577.22341,"atl_date":"2015-01-14T00:00:00.000Z","roi":null,"last_updated":"2022-05-11T07:01:33.238Z"},{"id":"uniswap","symbol":"uni","name":"Uniswap","image":"https://assets.coingecko.com/coins/images/12504/large/uniswap-uni.png?1600306604","current_price":5.72,"market_cap":2616468527,"market_cap_rank":34,"fully_diluted_valuation":5731715733,"total_volume":233364251,"high_24h":6.6,"low_24h":5.73,"price_change_24h":-0.8350499906535411,"price_change_percentage_24h":-12.73542,"market_cap_change_24h":-376382829.353806,"market_cap_change_percentage_24h":-12.57606,"circulating_supply":456489583.4010546,"total_supply":1000000000.0,"max_supply":1000000000.0,"ath":44.92,"ath_change_percentage":-87.26115,"ath_date":"2021-05-03T05:25:04.822Z","atl":1.03,"atl_change_percentage":455.44622,"atl_date":"2020-09-17T01:20:38.214Z","roi":null,"last_updated":"2022-05-11T07:01:44.896Z"},{"id":"frax","symbol":"frax","name":"Frax","image":"https://assets.coingecko.com/coins/images/13422/large/frax_logo.png?1608476506","current_price":0.991705,"market_cap":2488058378,"market_cap_rank":36,"fully_diluted_valuation":2488058378,"total_volume":52735328,"high_24h":1.007,"low_24h":0.990171,"price_change_24h":-0.00813850210205991,"price_change_percentage_24h":-0.81398,"market_cap_change_24h":-150758024.47504807,"market_cap_change_percentage_24h":-5.71309,"circulating_supply":2508870397.95036,"total_supply":2508870397.95036,"max_supply":2508870397.95036,"ath":1.14,"ath_change_percentage":-13.04279,"ath_date":"2021-02-07T12:55:35.766Z","atl":0.891635,"atl_change_percentage":11.22312,"atl_date":"2021-12-04T05:33:57.315Z","roi":null,"last_updated":"2022-05-11T07:01:13.629Z"},{"id":"vechain","symbol":"vet","name":"VeChain","image":"https://assets.coingecko.com/coins/images/1167/large/VeChain-Logo-768x725.png?1547035194","current_price":0.03702966,"market_cap":2472402894,"market_cap_rank":35,"fully_diluted_valuation":3211297002,"total_volume":395129003,"high_24h":0.04283719,"low_24h":0.03712581,"price_change_24h":-0.005807536331290677,"price_change_percentage_24h":-13.55723,"market_cap_change_24h":-395008651.7559061,"market_cap_change_percentage_24h":-13.77579,"circulating_supply":66760741299.0,"total_supply":85985041177.0,"max_supply":86712634466.0,"ath":0.280991,"ath_change_percentage":-86.78755,"ath_date":"2021-04-19T01:08:21.675Z","atl":0.00191713,"atl_change_percentage":1836.52729,"atl_date":"2020-03-13T02:29:59.652Z","roi":{"times":4.625621305876175,"currency":"eth","percentage":462.5621305876175},"last_updated":"2022-05-11T07:02:38.425Z"},{"id":"elrond-erd-2","symbol":"egld","name":"Elrond","image":"https://assets.coingecko.com/coins/images/12335/large/elrond3_360.png?1626341589","current_price":106.94,"market_cap":2371547190,"market_cap_rank":37,"fully_diluted_valuation":null,"total_volume":123733565,"high_24h":116.55,"low_24h":106.11,"price_change_24h":-8.961214909522255,"price_change_percentage_24h":-7.73172,"market_cap_change_24h":-220068043.1697631,"market_cap_change_percentage_24h":-8.49154,"circulating_supply":22321394.0,"total_supply":23651394.0,"max_supply":null,"ath":545.64,"ath_change_percentage":-80.40082,"ath_date":"2021-11-23T10:33:26.737Z","atl":6.51,"atl_change_percentage":1543.55953,"atl_date":"2020-10-07T01:44:53.554Z","roi":null,"last_updated":"2022-05-11T07:01:06.361Z"},{"id":"apecoin","symbol":"ape","name":"ApeCoin","image":"https://assets.coingecko.com/coins/images/24383/large/apecoin.jpg?1647476455","current_price":8.0,"market_cap":2281175563,"market_cap_rank":38,"fully_diluted_valuation":8008515417,"total_volume":1564591408,"high_24h":10.12,"low_24h":8.01,"price_change_24h":-1.275186323608695,"price_change_percentage_24h":-13.746,"market_cap_change_24h":-361258334.04589605,"market_cap_change_percentage_24h":-13.67142,"circulating_supply":284843750.0,"total_supply":1000000000.0,"max_supply":1000000000.0,"ath":26.7,"ath_change_percentage":-69.34545,"ath_date":"2022-04-28T21:44:21.164Z","atl":6.21,"atl_change_percentage":31.71198,"atl_date":"2022-03-17T13:30:22.320Z","roi":null,"last_updated":"2022-05-11T07:01:42.125Z"},{"id":"internet-computer","symbol":"icp","name":"Internet Computer","image":"https://assets.coingecko.com/coins/images/14495/large/Internet_Computer_logo.png?1620703073","current_price":9.61,"market_cap":2216979400,"market_cap_rank":40,"fully_diluted_valuation":4511276086,"total_volume":260686183,"high_24h":11.55,"low_24h":9.61,"price_change_24h":-1.543228617867534,"price_change_percentage_24h":-13.83768,"market_cap_change_24h":-349584207.2148247,"market_cap_change_percentage_24h":-13.62071,"circulating_supply":230586004.835593,"total_supply":481233872.700366,"max_supply":469213710.0,"ath":700.65,"ath_change_percentage":-98.58901,"ath_date":"2021-05-10T16:05:53.653Z","atl":9.75,"atl_change_percentage":1.41168,"atl_date":"2022-05-10T00:34:10.710Z","roi":null,"last_updated":"2022-05-11T07:01:41.811Z"},{"id":"hedera-hashgraph","symbol":"hbar","name":"Hedera","image":"https://assets.coingecko.com/coins/images/3688/large/hbar.png?1637045634","current_price":0.105937,"market_cap":2202372861,"market_cap_rank":39,"fully_diluted_valuation":null,"total_volume":74653002,"high_24h":0.121635,"low_24h":0.105861,"price_change_24h":-0.01213001764859678,"price_change_percentage_24h":-10.27381,"market_cap_change_24h":-243350362.91982985,"market_cap_change_percentage_24h":-9.95004,"circulating_supply":20804406793.3046,"total_supply":50000000000.0,"max_supply":null,"ath":0.569229,"ath_change_percentage":-81.40276,"ath_date":"2021-09-15T10:40:28.318Z","atl":0.00986111,"atl_change_percentage":973.51888,"atl_date":"2020-01-02T17:30:24.852Z","roi":null,"last_updated":"2022-05-11T07:02:40.431Z"},{"id":"filecoin","symbol":"fil","name":"Filecoin","image":"https://assets.coingecko.com/coins/images/12817/large/filecoin.png?1602753933","current_price":10.4,"market_cap":2096622954,"market_cap_rank":41,"fully_diluted_valuation":20482735133,"total_volume":516341088,"high_24h":12.27,"low_24h":10.41,"price_change_24h":-1.868755082971683,"price_change_percentage_24h":-15.23363,"market_cap_change_24h":-373511790.50539565,"market_cap_change_percentage_24h":-15.12111,"circulating_supply":201626569.0,"total_supply":1969769338.0,"max_supply":1969769338.0,"ath":236.84,"ath_change_percentage":-95.60941,"ath_date":"2021-04-01T13:29:41.564Z","atl":10.41,"atl_change_percentage":-0.10975,"atl_date":"2022-05-11T06:59:51.410Z","roi":null,"last_updated":"2022-05-11T07:02:02.981Z"},{"id":"compound-ether","symbol":"ceth","name":"cETH","image":"https://assets.coingecko.com/coins/images/10643/large/ceth2.JPG?1581389598","current_price":47.82,"market_cap":1989649960,"market_cap_rank":43,"fully_diluted_valuation":null,"total_volume":1082.95,"high_24h":49.1,"low_24h":45.55,"price_change_24h":-0.49426938728874603,"price_change_percentage_24h":-1.023,"market_cap_change_24h":-14504994.031815052,"market_cap_change_percentage_24h":-0.72375,"circulating_supply":41605753.2679434,"total_supply":41605753.2679434,"max_supply":null,"ath":97.75,"ath_change_percentage":-51.07802,"ath_date":"2021-11-21T12:39:57.508Z","atl":1.89,"atl_change_percentage":2435.21765,"atl_date":"2020-03-13T02:22:33.711Z","roi":null,"last_updated":"2022-05-11T07:02:21.449Z"},{"id":"the-sandbox","symbol":"sand","name":"The Sandbox","image":"https://assets.coingecko.com/coins/images/12129/large/sandbox_logo.jpg?1597397942","current_price":1.6,"market_cap":1966686850,"market_cap_rank":42,"fully_diluted_valuation":4806410885,"total_volume":448003504,"high_24h":1.91,"low_24h":1.6,"price_change_24h":-0.2893420662554731,"price_change_percentage_24h":-15.30991,"market_cap_change_24h":-364940969.57157755,"market_cap_change_percentage_24h":-15.65177,"circulating_supply":1227539778.2233226,"total_supply":3000000000.0,"max_supply":3000000000.0,"ath":8.4,"ath_change_percentage":-80.93845,"ath_date":"2021-11-25T06:04:40.957Z","atl":0.02897764,"atl_change_percentage":5423.42777,"atl_date":"2020-11-04T15:59:14.441Z","roi":null,"last_updated":"2022-05-11T07:02:10.300Z"},{"id":"magic-internet-money","symbol":"mim","name":"Magic Internet Money","image":"https://assets.coingecko.com/coins/images/16786/large/mimlogopng.png?1624979612","current_price":1.002,"market_cap":1912825613,"market_cap_rank":44,"fully_diluted_valuation":null,"total_volume":299232526,"high_24h":1.005,"low_24h":0.986838,"price_change_24h":0.0029317,"price_change_percentage_24h":0.29338,"market_cap_change_24h":-33808667.49097061,"market_cap_change_percentage_24h":-1.73678,"circulating_supply":1907682420.92554,"total_supply":1907682420.92554,"max_supply":null,"ath":1.041,"ath_change_percentage":-4.18384,"ath_date":"2021-10-06T13:25:17.751Z","atl":0.919196,"atl_change_percentage":8.51863,"atl_date":"2021-12-04T05:29:56.806Z","roi":null,"last_updated":"2022-05-11T07:01:33.191Z"},{"id":"theta-fuel","symbol":"tfuel","name":"Theta Fuel","image":"https://assets.coingecko.com/coins/images/8029/large/1_0YusgngOrriVg4ZYx4wOFQ.png?1553483622","current_price":0.092764,"market_cap":1886178774,"market_cap_rank":45,"fully_diluted_valuation":null,"total_volume":18194845,"high_24h":0.106783,"low_24h":0.092626,"price_change_24h":-0.012823303736894304,"price_change_percentage_24h":-12.14469,"market_cap_change_24h":49552231,"market_cap_change_percentage_24h":2.698,"circulating_supply":0.0,"total_supply":5301200000.0,"max_supply":null,"ath":0.68159,"ath_change_percentage":-86.41036,"ath_date":"2021-06-09T06:50:55.818Z","atl":0.00090804,"atl_change_percentage":10100.62064,"atl_date":"2020-03-13T02:30:37.972Z","roi":null,"last_updated":"2022-05-11T07:01:53.839Z"},{"id":"defichain","symbol":"dfi","name":"DeFiChain","image":"https://assets.coingecko.com/coins/images/11757/large/symbol-defi-blockchain_200.png?1597306538","current_price":3.46,"market_cap":1815175187,"market_cap_rank":46,"fully_diluted_valuation":null,"total_volume":44884206,"high_24h":3.82,"low_24h":3.47,"price_change_24h":-0.359204603637981,"price_change_percentage_24h":-9.41202,"market_cap_change_24h":-168974860.76998425,"market_cap_change_percentage_24h":-8.51623,"circulating_supply":518462416.561693,"total_supply":1200000000.0,"max_supply":null,"ath":5.61,"ath_change_percentage":-38.14659,"ath_date":"2021-12-06T03:05:01.038Z","atl":0.162998,"atl_change_percentage":2030.06993,"atl_date":"2020-07-16T10:24:06.014Z","roi":null,"last_updated":"2022-05-11T07:02:33.376Z"},{"id":"tezos","symbol":"xtz","name":"Tezos","image":"https://assets.coingecko.com/coins/images/976/large/Tezos-logo.png?1547034862","current_price":2.01,"market_cap":1783788467,"market_cap_rank":47,"fully_diluted_valuation":null,"total_volume":144877411,"high_24h":2.29,"low_24h":2.01,"price_change_24h":-0.22746143202741997,"price_change_percentage_24h":-10.16339,"market_cap_change_24h":-199713301.93556762,"market_cap_change_percentage_24h":-10.06872,"circulating_supply":886448958.940269,"total_supply":null,"max_supply":null,"ath":9.12,"ath_change_percentage":-77.92594,"ath_date":"2021-10-04T00:41:18.025Z","atl":0.350476,"atl_change_percentage":474.15789,"atl_date":"2018-12-07T00:00:00.000Z","roi":{"times":3.277842715539536,"currency":"usd","percentage":327.7842715539536},"last_updated":"2022-05-11T07:01:43.880Z"},{"id":"axie-infinity","symbol":"axs","name":"Axie Infinity","image":"https://assets.coingecko.com/coins/images/13029/large/axie_infinity_logo.png?1604471082","current_price":21.76,"market_cap":1708304537,"market_cap_rank":48,"fully_diluted_valuation":5886711560,"total_volume":455308865,"high_24h":28.2,"low_24h":21.83,"price_change_24h":-5.962293810007868,"price_change_percentage_24h":-21.50952,"market_cap_change_24h":-466275488.9141309,"market_cap_change_percentage_24h":-21.44209,"circulating_supply":78353121.30553937,"total_supply":270000000.0,"max_supply":270000000.0,"ath":164.9,"ath_change_percentage":-86.77808,"ath_date":"2021-11-06T19:29:29.482Z","atl":0.123718,"atl_change_percentage":17522.83185,"atl_date":"2020-11-06T08:05:43.662Z","roi":null,"last_updated":"2022-05-11T07:02:56.087Z"},{"id":"theta-token","symbol":"theta","name":"Theta Network","image":"https://assets.coingecko.com/coins/images/2538/large/theta-token-logo.png?1548387191","current_price":1.61,"market_cap":1612933200,"market_cap_rank":49,"fully_diluted_valuation":null,"total_volume":247907032,"high_24h":1.93,"low_24h":1.62,"price_change_24h":-0.268832373455941,"price_change_percentage_24h":-14.28034,"market_cap_change_24h":-269455750.6002948,"market_cap_change_percentage_24h":-14.31456,"circulating_supply":1000000000.0,"total_supply":1000000000.0,"max_supply":null,"ath":15.72,"ath_change_percentage":-89.73943,"ath_date":"2021-04-16T13:15:11.190Z","atl":0.04039979,"atl_change_percentage":3892.42921,"atl_date":"2020-03-13T02:24:16.483Z","roi":{"times":9.758016849293034,"currency":"usd","percentage":975.8016849293033},"last_updated":"2022-05-11T07:02:44.205Z"},{"id":"eos","symbol":"eos","name":"EOS","image":"https://assets.coingecko.com/coins/images/738/large/eos-eos-logo.png?1547034481","current_price":1.62,"market_cap":1611096371,"market_cap_rank":50,"fully_diluted_valuation":null,"total_volume":593219642,"high_24h":1.81,"low_24h":1.63,"price_change_24h":-0.1665340721191666,"price_change_percentage_24h":-9.31691,"market_cap_change_24h":-170272990.3762257,"market_cap_change_percentage_24h":-9.55854,"circulating_supply":993948660.2058,"total_supply":null,"max_supply":null,"ath":22.71,"ath_change_percentage":-92.83436,"ath_date":"2018-04-29T07:50:33.540Z","atl":0.5024,"atl_change_percentage":223.92683,"atl_date":"2017-10-23T00:00:00.000Z","roi":{"times":0.6372777956349667,"currency":"usd","percentage":63.72777956349667},"last_updated":"2022-05-11T07:00:24.065Z"},{"id":"pancakeswap-token","symbol":"cake","name":"PancakeSwap","image":"https://assets.coingecko.com/coins/images/12632/large/pancakeswap-cake-logo_%281%29.png?1629359065","current_price":5.38,"market_cap":1587721428,"market_cap_rank":51,"fully_diluted_valuation":null,"total_volume":159354743,"high_24h":6.22,"low_24h":5.39,"price_change_24h":-0.8413303593106729,"price_change_percentage_24h":-13.53369,"market_cap_change_24h":-244549398.88959837,"market_cap_change_percentage_24h":-13.34679,"circulating_supply":294326377.720477,"total_supply":null,"max_supply":null,"ath":43.96,"ath_change_percentage":-87.77373,"ath_date":"2021-04-30T10:08:22.934Z","atl":0.194441,"atl_change_percentage":2664.4605,"atl_date":"2020-11-03T14:29:34.165Z","roi":null,"last_updated":"2022-05-11T07:01:51.569Z"},{"id":"decentraland","symbol":"mana","name":"Decentraland","image":"https://assets.coingecko.com/coins/images/878/large/decentraland-mana.png?1550108745","current_price":1.027,"market_cap":1555187234,"market_cap_rank":52,"fully_diluted_valuation":2259363683,"total_volume":438399130,"high_24h":1.22,"low_24h":1.03,"price_change_24h":-0.16724487214894213,"price_change_percentage_24h":-14.00052,"market_cap_change_24h":-253423935.1989987,"market_cap_change_percentage_24h":-14.01207,"circulating_supply":1509971503.0379589,"total_supply":2193674627.32015,"max_supply":2193674627.32015,"ath":5.85,"ath_change_percentage":-82.35277,"ath_date":"2021-11-25T10:04:18.534Z","atl":0.00923681,"atl_change_percentage":11078.18644,"atl_date":"2017-10-31T00:00:00.000Z","roi":{"times":50.3658450701615,"currency":"usd","percentage":5036.58450701615},"last_updated":"2022-05-11T07:02:53.368Z"},{"id":"the-graph","symbol":"grt","name":"The Graph","image":"https://assets.coingecko.com/coins/images/13397/large/Graph_Token.png?1608145566","current_price":0.217576,"market_cap":1519362451,"market_cap_rank":53,"fully_diluted_valuation":2192562236,"total_volume":210563405,"high_24h":0.269041,"low_24h":0.219256,"price_change_24h":-0.042497643173236066,"price_change_percentage_24h":-16.34063,"market_cap_change_24h":-308197562.4902127,"market_cap_change_percentage_24h":-16.86388,"circulating_supply":6929620630.0,"total_supply":10000000000.0,"max_supply":10000000000.0,"ath":2.84,"ath_change_percentage":-92.3429,"ath_date":"2021-02-12T07:28:45.775Z","atl":0.103254,"atl_change_percentage":110.71932,"atl_date":"2020-12-17T21:28:41.332Z","roi":null,"last_updated":"2022-05-11T07:02:02.721Z"},{"id":"chain-2","symbol":"xcn","name":"Chain","image":"https://assets.coingecko.com/coins/images/24210/large/Chain_icon_200x200.png?1646895054","current_price":0.085097,"market_cap":1442810865,"market_cap_rank":54,"fully_diluted_valuation":5861817930,"total_volume":151696639,"high_24h":0.08817,"low_24h":0.073129,"price_change_24h":0.01081211,"price_change_percentage_24h":14.55492,"market_cap_change_24h":190426092,"market_cap_change_percentage_24h":15.20508,"circulating_supply":16957724335.443073,"total_supply":68895442185.0,"max_supply":68895442185.0,"ath":0.116203,"ath_change_percentage":-26.7942,"ath_date":"2022-04-19T17:19:07.914Z","atl":0.04451621,"atl_change_percentage":91.09321,"atl_date":"2022-03-15T12:18:14.392Z","roi":null,"last_updated":"2022-05-11T07:02:34.435Z"},{"id":"compound-usd-coin","symbol":"cusdc","name":"cUSDC","image":"https://assets.coingecko.com/coins/images/9442/large/Compound_USDC.png?1567581577","current_price":0.02257707,"market_cap":1424299347,"market_cap_rank":55,"fully_diluted_valuation":null,"total_volume":0.0,"high_24h":0.02280986,"low_24h":0.02253986,"price_change_24h":-4.416739758564e-06,"price_change_percentage_24h":-0.01956,"market_cap_change_24h":27961662,"market_cap_change_percentage_24h":2.0025,"circulating_supply":62878210779.5543,"total_supply":62878210779.5543,"max_supply":null,"ath":0.058843,"ath_change_percentage":-61.5051,"ath_date":"2020-10-21T11:24:27.820Z","atl":0.00620705,"atl_change_percentage":264.93503,"atl_date":"2021-03-04T08:11:37.438Z","roi":null,"last_updated":"2022-05-11T07:01:55.159Z"},{"id":"aave","symbol":"aave","name":"Aave","image":"https://assets.coingecko.com/coins/images/12645/large/AAVE.png?1601374110","current_price":100.13,"market_cap":1376406725,"market_cap_rank":56,"fully_diluted_valuation":1605739851,"total_volume":351970133,"high_24h":116.74,"low_24h":100.36,"price_change_24h":-15.74193779954581,"price_change_percentage_24h":-13.58615,"market_cap_change_24h":-216084504.7390554,"market_cap_change_percentage_24h":-13.56896,"circulating_supply":13714866.438445605,"total_supply":16000000.0,"max_supply":16000000.0,"ath":661.69,"ath_change_percentage":-84.86814,"ath_date":"2021-05-18T21:19:59.514Z","atl":26.02,"atl_change_percentage":284.75761,"atl_date":"2020-11-05T09:20:11.928Z","roi":null,"last_updated":"2022-05-11T07:01:48.323Z"},{"id":"kucoin-shares","symbol":"kcs","name":"KuCoin Token","image":"https://assets.coingecko.com/coins/images/1047/large/sa9z79.png?1610678720","current_price":13.5,"market_cap":1350808069,"market_cap_rank":57,"fully_diluted_valuation":null,"total_volume":15450014,"high_24h":15.16,"low_24h":13.43,"price_change_24h":-1.0876565623261136,"price_change_percentage_24h":-7.4545,"market_cap_change_24h":-85081738.7911439,"market_cap_change_percentage_24h":-5.92537,"circulating_supply":98141682.9536053,"total_supply":145641682.953521,"max_supply":null,"ath":28.83,"ath_change_percentage":-53.40749,"ath_date":"2021-12-01T15:09:35.541Z","atl":0.342863,"atl_change_percentage":3817.76523,"atl_date":"2019-02-07T00:00:00.000Z","roi":null,"last_updated":"2022-05-11T07:02:20.662Z"},{"id":"flow","symbol":"flow","name":"Flow","image":"https://assets.coingecko.com/coins/images/13446/large/5f6294c0c7a8cda55cb1c936_Flow_Wordmark.png?1631696776","current_price":3.64,"market_cap":1348927284,"market_cap_rank":58,"fully_diluted_valuation":null,"total_volume":256555574,"high_24h":4.49,"low_24h":3.66,"price_change_24h":-0.2188287587219575,"price_change_percentage_24h":-5.67228,"market_cap_change_24h":-65230859.45936394,"market_cap_change_percentage_24h":-4.6127,"circulating_supply":364061129.0,"total_supply":1372066760.81725,"max_supply":null,"ath":42.4,"ath_change_percentage":-91.4168,"ath_date":"2021-04-05T13:49:10.098Z","atl":3.32,"atl_change_percentage":9.72039,"atl_date":"2022-05-10T00:32:28.987Z","roi":null,"last_updated":"2022-05-11T07:01:37.268Z"},{"id":"klay-token","symbol":"klay","name":"Klaytn","image":"https://assets.coingecko.com/coins/images/9672/large/klaytn.jpeg?1642775250","current_price":0.472655,"market_cap":1322594845,"market_cap_rank":59,"fully_diluted_valuation":null,"total_volume":84911425,"high_24h":0.537485,"low_24h":0.473057,"price_change_24h":-0.05041889167370749,"price_change_percentage_24h":-9.63896,"market_cap_change_24h":-156337843.06301498,"market_cap_change_percentage_24h":-10.57099,"circulating_supply":2798224045.4,"total_supply":null,"max_supply":null,"ath":4.34,"ath_change_percentage":-89.10659,"ath_date":"2021-03-30T03:44:28.828Z","atl":0.06044,"atl_change_percentage":682.02958,"atl_date":"2020-04-29T08:19:34.574Z","roi":null,"last_updated":"2022-05-11T07:01:33.767Z"},{"id":"bittorrent","symbol":"btt","name":"BitTorrent","image":"https://assets.coingecko.com/coins/images/22457/large/btt_logo.png?1643857231","current_price":1.43e-06,"market_cap":1322443656,"market_cap_rank":60,"fully_diluted_valuation":1408860663,"total_volume":185277193,"high_24h":1.54e-06,"low_24h":1.42e-06,"price_change_24h":-1.04395046846e-07,"price_change_percentage_24h":-6.8185,"market_cap_change_24h":-97924361.37542963,"market_cap_change_percentage_24h":-6.8943,"circulating_supply":929275160714000.0,"total_supply":990000000000000.0,"max_supply":990000000000000.0,"ath":3.43e-06,"ath_change_percentage":-57.75681,"ath_date":"2022-01-21T04:00:31.909Z","atl":1.41e-06,"atl_change_percentage":2.44415,"atl_date":"2022-05-10T00:34:07.614Z","roi":null,"last_updated":"2022-05-11T07:02:22.246Z"},{"id":"true-usd","symbol":"tusd","name":"TrueUSD","image":"https://assets.coingecko.com/coins/images/3449/large/tusd.png?1618395665","current_price":1.002,"market_cap":1300553537,"market_cap_rank":61,"fully_diluted_valuation":null,"total_volume":325872523,"high_24h":1.009,"low_24h":0.992021,"price_change_24h":-0.001743523108783673,"price_change_percentage_24h":-0.17378,"market_cap_change_24h":-3318431.383621216,"market_cap_change_percentage_24h":-0.25451,"circulating_supply":1297599662.03407,"total_supply":1297599662.03407,"max_supply":null,"ath":1.62,"ath_change_percentage":-38.07423,"ath_date":"2018-08-26T20:41:09.375Z","atl":0.88355,"atl_change_percentage":13.43745,"atl_date":"2020-03-12T10:47:51.380Z","roi":null,"last_updated":"2022-05-11T07:01:51.952Z"},{"id":"huobi-token","symbol":"ht","name":"Huobi Token","image":"https://assets.coingecko.com/coins/images/2822/large/huobi-token-logo.png?1547036992","current_price":7.96,"market_cap":1236535681,"market_cap_rank":62,"fully_diluted_valuation":3983041319,"total_volume":71236198,"high_24h":8.47,"low_24h":7.97,"price_change_24h":-0.34428424898245424,"price_change_percentage_24h":-4.14581,"market_cap_change_24h":-55131298.94255042,"market_cap_change_percentage_24h":-4.26823,"circulating_supply":155225063.25441208,"total_supply":500000000.0,"max_supply":500000000.0,"ath":39.66,"ath_change_percentage":-79.91445,"ath_date":"2021-05-12T14:42:21.586Z","atl":0.90862,"atl_change_percentage":776.72339,"atl_date":"2019-01-30T00:00:00.000Z","roi":{"times":7.040508071093968,"currency":"usd","percentage":704.0508071093967},"last_updated":"2022-05-11T07:02:17.621Z"},{"id":"convex-finance","symbol":"cvx","name":"Convex Finance","image":"https://assets.coingecko.com/coins/images/15585/large/convex.png?1621256328","current_price":19.76,"market_cap":1214541257,"market_cap_rank":65,"fully_diluted_valuation":1993413422,"total_volume":21576911,"high_24h":21.97,"low_24h":19.8,"price_change_24h":-1.0299203606244802,"price_change_percentage_24h":-4.95496,"market_cap_change_24h":-55452111.282227755,"market_cap_change_percentage_24h":-4.36633,"circulating_supply":60927715.39125189,"total_supply":89772770.8041561,"max_supply":100000000.0,"ath":60.09,"ath_change_percentage":-66.14514,"ath_date":"2022-01-01T18:04:03.030Z","atl":1.9,"atl_change_percentage":969.04361,"atl_date":"2021-07-20T13:17:29.183Z","roi":null,"last_updated":"2022-05-11T07:02:49.674Z"},{"id":"fantom","symbol":"ftm","name":"Fantom","image":"https://assets.coingecko.com/coins/images/4001/large/Fantom.png?1558015016","current_price":0.4775,"market_cap":1214308353,"market_cap_rank":63,"fully_diluted_valuation":1517196890,"total_volume":579079295,"high_24h":0.612823,"low_24h":0.479104,"price_change_24h":-0.12165574576537597,"price_change_percentage_24h":-20.30451,"market_cap_change_24h":-309980164.4553375,"market_cap_change_percentage_24h":-20.33606,"circulating_supply":2541152731.01,"total_supply":3175000000.0,"max_supply":3175000000.0,"ath":3.46,"ath_change_percentage":-86.1834,"ath_date":"2021-10-28T05:19:39.845Z","atl":0.00190227,"atl_change_percentage":25020.37472,"atl_date":"2020-03-13T02:25:38.280Z","roi":{"times":14.91668126514752,"currency":"usd","percentage":1491.668126514752},"last_updated":"2022-05-11T07:02:54.217Z"},{"id":"thorchain","symbol":"rune","name":"THORChain","image":"https://assets.coingecko.com/coins/images/6595/large/RUNE.png?1614160507","current_price":3.98,"market_cap":1197297214,"market_cap_rank":64,"fully_diluted_valuation":1990484810,"total_volume":253976052,"high_24h":5.32,"low_24h":3.98,"price_change_24h":-1.3403554660165793,"price_change_percentage_24h":-25.21077,"market_cap_change_24h":-406256268.69613504,"market_cap_change_percentage_24h":-25.33475,"circulating_supply":300755174.9386705,"total_supply":500000000.0,"max_supply":500000000.0,"ath":20.87,"ath_change_percentage":-80.92269,"ath_date":"2021-05-19T00:30:09.436Z","atl":0.00851264,"atl_change_percentage":46665.40159,"atl_date":"2019-09-28T00:00:00.000Z","roi":{"times":103.63796474763829,"currency":"usd","percentage":10363.796474763829},"last_updated":"2022-05-11T07:01:56.300Z"},{"id":"huobi-btc","symbol":"hbtc","name":"Huobi BTC","image":"https://assets.coingecko.com/coins/images/12407/large/Unknown-5.png?1599624896","current_price":30230,"market_cap":1190056165,"market_cap_rank":66,"fully_diluted_valuation":1190056165,"total_volume":31180,"high_24h":32915,"low_24h":30375,"price_change_24h":-2644.4834016384593,"price_change_percentage_24h":-8.04412,"market_cap_change_24h":-103762727.82220364,"market_cap_change_percentage_24h":-8.01988,"circulating_supply":38970.487704742,"total_supply":38970.487704742,"max_supply":38970.487704742,"ath":166135,"ath_change_percentage":-81.71646,"ath_date":"2022-04-21T18:59:43.859Z","atl":11209.02,"atl_change_percentage":170.98976,"atl_date":"2020-10-12T03:56:16.768Z","roi":null,"last_updated":"2022-05-11T07:02:51.315Z"},{"id":"bitcoin-cash-sv","symbol":"bsv","name":"Bitcoin SV","image":"https://assets.coingecko.com/coins/images/6799/large/BSV.png?1558947902","current_price":59.95,"market_cap":1134919155,"market_cap_rank":67,"fully_diluted_valuation":null,"total_volume":177730238,"high_24h":65.48,"low_24h":59.56,"price_change_24h":-5.314827223204595,"price_change_percentage_24h":-8.14376,"market_cap_change_24h":-115580898.04063559,"market_cap_change_percentage_24h":-9.24277,"circulating_supply":19055876.644239,"total_supply":21000000.0,"max_supply":null,"ath":489.75,"ath_change_percentage":-87.78157,"ath_date":"2021-04-16T17:09:04.630Z","atl":42.02,"atl_change_percentage":42.41714,"atl_date":"2018-11-23T00:00:00.000Z","roi":null,"last_updated":"2022-05-11T07:01:51.897Z"},{"id":"maker","symbol":"mkr","name":"Maker","image":"https://assets.coingecko.com/coins/images/1364/large/Mark_Maker.png?1585191826","current_price":1213.46,"market_cap":1094705177,"market_cap_rank":69,"fully_diluted_valuation":1221343589,"total_volume":177652928,"high_24h":1296.68,"low_24h":1106.52,"price_change_24h":-16.609358725239417,"price_change_percentage_24h":-1.35028,"market_cap_change_24h":-15784411.514943361,"market_cap_change_percentage_24h":-1.42139,"circulating_supply":901310.9472893132,"total_supply":977631.036950888,"max_supply":1005577.0,"ath":6292.31,"ath_change_percentage":-80.69757,"ath_date":"2021-05-03T21:54:29.333Z","atl":168.36,"atl_change_percentage":621.42281,"atl_date":"2020-03-16T20:52:36.527Z","roi":null,"last_updated":"2022-05-11T07:02:14.027Z"},{"id":"zcash","symbol":"zec","name":"Zcash","image":"https://assets.coingecko.com/coins/images/486/large/circle-zcash-color.png?1547034197","current_price":87.87,"market_cap":1089813877,"market_cap_rank":68,"fully_diluted_valuation":1841404934,"total_volume":180389418,"high_24h":104.29,"low_24h":87.85,"price_change_24h":-16.175075637766597,"price_change_percentage_24h":-15.54694,"market_cap_change_24h":-200524960.02759266,"market_cap_change_percentage_24h":-15.54049,"circulating_supply":12428603.2912968,"total_supply":21000000.0,"max_supply":21000000.0,"ath":3191.93,"ath_change_percentage":-97.24789,"ath_date":"2016-10-29T00:00:00.000Z","atl":19.75,"atl_change_percentage":344.70419,"atl_date":"2020-03-13T02:20:55.002Z","roi":null,"last_updated":"2022-05-11T07:02:51.313Z"},{"id":"ecash","symbol":"xec","name":"eCash","image":"https://assets.coingecko.com/coins/images/16646/large/Logo_final-22.png?1628239446","current_price":5.651e-05,"market_cap":1077080112,"market_cap_rank":71,"fully_diluted_valuation":1186940363,"total_volume":20750951,"high_24h":6.319e-05,"low_24h":5.652e-05,"price_change_24h":-5.533091235392e-06,"price_change_percentage_24h":-8.91883,"market_cap_change_24h":-102847991.98636985,"market_cap_change_percentage_24h":-8.71646,"circulating_supply":19056292173313.0,"total_supply":21000000000000.0,"max_supply":21000000000000.0,"ath":0.00038001,"ath_change_percentage":-84.67798,"ath_date":"2021-09-04T17:09:31.137Z","atl":1.847e-05,"atl_change_percentage":215.24622,"atl_date":"2021-07-20T20:49:46.212Z","roi":null,"last_updated":"2022-05-11T07:01:54.672Z"},{"id":"waves","symbol":"waves","name":"Waves","image":"https://assets.coingecko.com/coins/images/425/large/waves.png?1548386117","current_price":10.68,"market_cap":1070028210,"market_cap_rank":70,"fully_diluted_valuation":null,"total_volume":466956462,"high_24h":13.38,"low_24h":10.7,"price_change_24h":-2.657997130145189,"price_change_percentage_24h":-19.92586,"market_cap_change_24h":-264698481.73887503,"market_cap_change_percentage_24h":-19.83166,"circulating_supply":100000000.0,"total_supply":100000000.0,"max_supply":null,"ath":61.3,"ath_change_percentage":-82.50689,"ath_date":"2022-03-31T14:34:44.545Z","atl":0.130878,"atl_change_percentage":8093.64723,"atl_date":"2016-08-02T00:00:00.000Z","roi":{"times":55.81616017637984,"currency":"usd","percentage":5581.616017637984},"last_updated":"2022-05-11T07:02:48.478Z"},{"id":"helium","symbol":"hnt","name":"Helium","image":"https://assets.coingecko.com/coins/images/4284/large/Helium_HNT.png?1612620071","current_price":10.47,"market_cap":1050877932,"market_cap_rank":72,"fully_diluted_valuation":2330885876,"total_volume":24280422,"high_24h":13.1,"low_24h":10.45,"price_change_24h":-2.2059072919023386,"price_change_percentage_24h":-17.40118,"market_cap_change_24h":-234902760.1096071,"market_cap_change_percentage_24h":-18.26927,"circulating_supply":100539361.984279,"total_supply":223000000.0,"max_supply":223000000.0,"ath":54.88,"ath_change_percentage":-80.95305,"ath_date":"2021-11-12T23:08:25.301Z","atl":0.113248,"atl_change_percentage":9129.68602,"atl_date":"2020-04-18T00:19:10.902Z","roi":null,"last_updated":"2022-05-11T07:02:33.402Z"},{"id":"cdai","symbol":"cdai","name":"cDAI","image":"https://assets.coingecko.com/coins/images/9281/large/cDAI.png?1576467585","current_price":0.02185852,"market_cap":1023216877,"market_cap_rank":73,"fully_diluted_valuation":null,"total_volume":3180.61,"high_24h":0.02218337,"low_24h":0.02192283,"price_change_24h":6.665e-05,"price_change_percentage_24h":0.3037,"market_cap_change_24h":16198111,"market_cap_change_percentage_24h":1.60852,"circulating_supply":46481795636.1645,"total_supply":46481795636.1645,"max_supply":null,"ath":0.03159087,"ath_change_percentage":-30.31757,"ath_date":"2020-10-12T21:29:00.007Z","atl":0.00728854,"atl_change_percentage":202.02579,"atl_date":"2020-03-18T04:29:40.819Z","roi":null,"last_updated":"2022-05-11T07:01:55.184Z"},{"id":"iota","symbol":"miota","name":"IOTA","image":"https://assets.coingecko.com/coins/images/692/large/IOTA_Swirl.png?1604238557","current_price":0.355882,"market_cap":1007940709,"market_cap_rank":75,"fully_diluted_valuation":null,"total_volume":131341124,"high_24h":0.438845,"low_24h":0.357048,"price_change_24h":-0.08114229222485408,"price_change_percentage_24h":-18.56699,"market_cap_change_24h":-210786844.68780684,"market_cap_change_percentage_24h":-17.29565,"circulating_supply":2779530283.277761,"total_supply":2779530283.0,"max_supply":null,"ath":5.25,"ath_change_percentage":-93.19749,"ath_date":"2017-12-19T00:00:00.000Z","atl":0.081637,"atl_change_percentage":337.35907,"atl_date":"2020-03-13T02:22:41.168Z","roi":{"times":7.6808341815360075,"currency":"btc","percentage":768.0834181536007},"last_updated":"2022-05-11T07:01:55.423Z"},{"id":"radix","symbol":"xrd","name":"Radix","image":"https://assets.coingecko.com/coins/images/4374/large/Radix.png?1629701658","current_price":0.100644,"market_cap":993177729,"market_cap_rank":74,"fully_diluted_valuation":2415448092,"total_volume":1058699,"high_24h":0.107738,"low_24h":0.09871,"price_change_24h":-0.002061658099125521,"price_change_percentage_24h":-2.00735,"market_cap_change_24h":-25144125.733148932,"market_cap_change_percentage_24h":-2.46917,"circulating_supply":9868258221.0562,"total_supply":12268235259.1566,"max_supply":24000000000.0,"ath":0.651264,"ath_change_percentage":-84.5464,"ath_date":"2021-11-14T16:09:27.130Z","atl":0.086235,"atl_change_percentage":16.70825,"atl_date":"2021-09-13T04:50:07.104Z","roi":null,"last_updated":"2022-05-11T07:00:51.835Z"},{"id":"paxos-standard","symbol":"usdp","name":"Pax Dollar","image":"https://assets.coingecko.com/coins/images/6013/large/Pax_Dollar.png?1629877204","current_price":1.003,"market_cap":973395897,"market_cap_rank":76,"fully_diluted_valuation":null,"total_volume":40060828,"high_24h":1.006,"low_24h":0.99419,"price_change_24h":-0.001117997804185755,"price_change_percentage_24h":-0.11132,"market_cap_change_24h":-5315309.093531251,"market_cap_change_percentage_24h":-0.54309,"circulating_supply":970402024.88,"total_supply":970402024.88,"max_supply":null,"ath":1.13,"ath_change_percentage":-11.04836,"ath_date":"2018-10-15T07:09:12.459Z","atl":0.863529,"atl_change_percentage":16.16115,"atl_date":"2021-05-19T13:14:42.046Z","roi":{"times":0.003187290040468,"currency":"usd","percentage":0.3187290040468},"last_updated":"2022-05-11T07:02:18.783Z"},{"id":"quant-network","symbol":"qnt","name":"Quant","image":"https://assets.coingecko.com/coins/images/3370/large/5ZOu7brX_400x400.jpg?1612437252","current_price":71.28,"market_cap":967852080,"market_cap_rank":77,"fully_diluted_valuation":1054329865,"total_volume":79150498,"high_24h":81.32,"low_24h":71.43,"price_change_24h":-10.039737243931171,"price_change_percentage_24h":-12.34645,"market_cap_change_24h":-136278226.69779813,"market_cap_change_percentage_24h":-12.34259,"circulating_supply":13413953.469289193,"total_supply":14612493.0,"max_supply":14612493.0,"ath":427.42,"ath_change_percentage":-83.27341,"ath_date":"2021-09-11T09:15:00.668Z","atl":0.215773,"atl_change_percentage":33033.47527,"atl_date":"2018-08-23T00:00:00.000Z","roi":{"times":12.286159962089883,"currency":"eth","percentage":1228.6159962089882},"last_updated":"2022-05-11T07:01:00.920Z"},{"id":"zilliqa","symbol":"zil","name":"Zilliqa","image":"https://assets.coingecko.com/coins/images/2687/large/Zilliqa-logo.png?1547036894","current_price":0.065876,"market_cap":941945877,"market_cap_rank":78,"fully_diluted_valuation":null,"total_volume":730471832,"high_24h":0.074803,"low_24h":0.065843,"price_change_24h":-0.008926874763819453,"price_change_percentage_24h":-11.93388,"market_cap_change_24h":-133607185.45567703,"market_cap_change_percentage_24h":-12.42218,"circulating_supply":14305939732.0147,"total_supply":21000000000.0,"max_supply":null,"ath":0.255376,"ath_change_percentage":-74.21722,"ath_date":"2021-05-06T17:33:45.940Z","atl":0.00239616,"atl_change_percentage":2647.85477,"atl_date":"2020-03-13T02:22:55.161Z","roi":{"times":2.375948833793097,"currency":"eth","percentage":237.5948833793097},"last_updated":"2022-05-11T07:01:40.752Z"},{"id":"neo","symbol":"neo","name":"NEO","image":"https://assets.coingecko.com/coins/images/480/large/NEO_512_512.png?1594357361","current_price":13.01,"market_cap":917033183,"market_cap_rank":79,"fully_diluted_valuation":null,"total_volume":114471879,"high_24h":15.01,"low_24h":13.0,"price_change_24h":-1.8349687331891698,"price_change_percentage_24h":-12.36376,"market_cap_change_24h":-130477576.91760159,"market_cap_change_percentage_24h":-12.45597,"circulating_supply":70530000.0,"total_supply":100000000.0,"max_supply":null,"ath":198.38,"ath_change_percentage":-93.44594,"ath_date":"2018-01-15T00:00:00.000Z","atl":0.078349,"atl_change_percentage":16494.93257,"atl_date":"2016-10-21T00:00:00.000Z","roi":{"times":360.2929598036183,"currency":"usd","percentage":36029.295980361836},"last_updated":"2022-05-11T07:02:21.979Z"},{"id":"nexo","symbol":"nexo","name":"NEXO","image":"https://assets.coingecko.com/coins/images/3695/large/nexo.png?1548086057","current_price":1.61,"market_cap":900180209,"market_cap_rank":80,"fully_diluted_valuation":1607464630,"total_volume":21579496,"high_24h":1.83,"low_24h":1.61,"price_change_24h":-0.15941948848549914,"price_change_percentage_24h":-9.0268,"market_cap_change_24h":-90603838.0213579,"market_cap_change_percentage_24h":-9.14466,"circulating_supply":560000010.0064,"total_supply":1000000000.0,"max_supply":1000000000.0,"ath":4.07,"ath_change_percentage":-60.48485,"ath_date":"2021-05-12T14:37:47.535Z","atl":0.04515276,"atl_change_percentage":3460.05828,"atl_date":"2018-09-13T00:00:00.000Z","roi":{"times":15.06648638243017,"currency":"usd","percentage":1506.648638243017},"last_updated":"2022-05-11T07:01:56.357Z"},{"id":"gatechain-token","symbol":"gt","name":"GateToken","image":"https://assets.coingecko.com/coins/images/8183/large/gt.png?1556085624","current_price":5.89,"market_cap":898750822,"market_cap_rank":81,"fully_diluted_valuation":null,"total_volume":11614467,"high_24h":6.04,"low_24h":5.79,"price_change_24h":-0.1015704219099165,"price_change_percentage_24h":-1.69549,"market_cap_change_24h":-11589290.064766645,"market_cap_change_percentage_24h":-1.27307,"circulating_supply":151758801.7378072,"total_supply":300000000.0,"max_supply":null,"ath":12.94,"ath_change_percentage":-54.50459,"ath_date":"2021-05-12T11:39:16.531Z","atl":0.25754,"atl_change_percentage":2186.22638,"atl_date":"2020-03-13T02:18:02.481Z","roi":null,"last_updated":"2022-05-11T07:02:20.131Z"},{"id":"neutrino","symbol":"usdn","name":"Neutrino USD","image":"https://assets.coingecko.com/coins/images/10117/large/78GWcZu.png?1600845716","current_price":0.952623,"market_cap":896171065,"market_cap_rank":82,"fully_diluted_valuation":null,"total_volume":13720061,"high_24h":0.976847,"low_24h":0.950633,"price_change_24h":-0.01690568093000744,"price_change_percentage_24h":-1.7437,"market_cap_change_24h":-14741905.794917107,"market_cap_change_percentage_24h":-1.61837,"circulating_supply":940740868.231352,"total_supply":940764394.919725,"max_supply":null,"ath":2.52,"ath_change_percentage":-62.20887,"ath_date":"2021-03-17T18:34:56.998Z","atl":0.728841,"atl_change_percentage":30.70378,"atl_date":"2022-04-04T18:19:50.217Z","roi":null,"last_updated":"2022-05-11T07:01:02.368Z"},{"id":"osmosis","symbol":"osmo","name":"Osmosis","image":"https://assets.coingecko.com/coins/images/16724/large/osmo.png?1632763885","current_price":2.39,"market_cap":878137850,"market_cap_rank":83,"fully_diluted_valuation":2391951667,"total_volume":228083878,"high_24h":3.08,"low_24h":2.39,"price_change_24h":-0.6853296174781573,"price_change_percentage_24h":-22.27062,"market_cap_change_24h":-249379831.8022082,"market_cap_change_percentage_24h":-22.1176,"circulating_supply":367121904.0,"total_supply":325000000.0,"max_supply":1000000000.0,"ath":11.25,"ath_change_percentage":-78.26968,"ath_date":"2022-03-04T05:12:18.707Z","atl":1.24,"atl_change_percentage":97.85301,"atl_date":"2021-07-20T10:21:24.662Z","roi":null,"last_updated":"2022-05-11T07:01:38.020Z"},{"id":"stepn","symbol":"gmt","name":"STEPN","image":"https://assets.coingecko.com/coins/images/23597/large/gmt.png?1644658792","current_price":1.43,"market_cap":856388084,"market_cap_rank":87,"fully_diluted_valuation":8563880845,"total_volume":2025818692,"high_24h":2.18,"low_24h":1.33,"price_change_24h":-0.5807169201972033,"price_change_percentage_24h":-28.82887,"market_cap_change_24h":-349751027.17231786,"market_cap_change_percentage_24h":-28.99757,"circulating_supply":600000000.0,"total_supply":6000000000.0,"max_supply":6000000000.0,"ath":4.11,"ath_change_percentage":-64.23168,"ath_date":"2022-04-28T03:29:53.820Z","atl":0.100826,"atl_change_percentage":1357.09384,"atl_date":"2022-03-11T06:04:31.100Z","roi":null,"last_updated":"2022-05-11T07:01:18.109Z"},{"id":"bitdao","symbol":"bit","name":"BitDAO","image":"https://assets.coingecko.com/coins/images/17627/large/bitdao.jpg?1628679607","current_price":0.898397,"market_cap":842753677,"market_cap_rank":84,"fully_diluted_valuation":8968113233,"total_volume":18271931,"high_24h":0.930508,"low_24h":0.898321,"price_change_24h":-0.025381335036931185,"price_change_percentage_24h":-2.74756,"market_cap_change_24h":-27641179.365327,"market_cap_change_percentage_24h":-3.17571,"circulating_supply":939722387.0407099,"total_supply":10000000000.0,"max_supply":10000000000.0,"ath":3.1,"ath_change_percentage":-70.94704,"ath_date":"2021-11-12T04:54:56.433Z","atl":0.893903,"atl_change_percentage":0.825,"atl_date":"2022-05-10T00:20:43.329Z","roi":null,"last_updated":"2022-05-11T07:00:25.390Z"},{"id":"frax-share","symbol":"fxs","name":"Frax Share","image":"https://assets.coingecko.com/coins/images/13423/large/frax_share.png?1608478989","current_price":13.9,"market_cap":838210583,"market_cap_rank":85,"fully_diluted_valuation":1375028991,"total_volume":56397350,"high_24h":19.3,"low_24h":13.91,"price_change_24h":-4.7867405426607785,"price_change_percentage_24h":-25.61135,"market_cap_change_24h":-288114365.5201229,"market_cap_change_percentage_24h":-25.58004,"circulating_supply":60256204.421220586,"total_supply":98846315.8025706,"max_supply":98846315.8025706,"ath":42.8,"ath_change_percentage":-67.49711,"ath_date":"2022-01-12T15:22:27.465Z","atl":1.5,"atl_change_percentage":825.46127,"atl_date":"2021-06-25T16:50:51.447Z","roi":null,"last_updated":"2022-05-11T07:02:45.430Z"},{"id":"arweave","symbol":"ar","name":"Arweave","image":"https://assets.coingecko.com/coins/images/4343/large/oRt6SiEN_400x400.jpg?1591059616","current_price":16.13,"market_cap":808008090,"market_cap_rank":86,"fully_diluted_valuation":1064261189,"total_volume":68721350,"high_24h":19.89,"low_24h":16.14,"price_change_24h":-3.7521565930719447,"price_change_percentage_24h":-18.87657,"market_cap_change_24h":-185342960.46379495,"market_cap_change_percentage_24h":-18.65835,"circulating_supply":50108502.0,"total_supply":64598643.0,"max_supply":66000000.0,"ath":89.24,"ath_change_percentage":-81.91181,"ath_date":"2021-11-05T04:14:42.689Z","atl":0.298788,"atl_change_percentage":5302.17044,"atl_date":"2020-01-31T06:47:36.543Z","roi":{"times":20.790769637408175,"currency":"usd","percentage":2079.0769637408175},"last_updated":"2022-05-11T07:01:39.277Z"},{"id":"celo","symbol":"celo","name":"Celo","image":"https://assets.coingecko.com/coins/images/11090/large/icon-celo-CELO-color-500.png?1592293590","current_price":1.76,"market_cap":780921789,"market_cap_rank":88,"fully_diluted_valuation":1778088703,"total_volume":80261374,"high_24h":2.15,"low_24h":1.77,"price_change_24h":-0.3478444075285023,"price_change_percentage_24h":-16.53632,"market_cap_change_24h":-152330336.34425092,"market_cap_change_percentage_24h":-16.32253,"circulating_supply":439191694.0,"total_supply":1000000000.0,"max_supply":1000000000.0,"ath":9.82,"ath_change_percentage":-82.12383,"ath_date":"2021-08-30T14:25:09.929Z","atl":0.800156,"atl_change_percentage":119.41639,"atl_date":"2020-05-22T04:15:27.736Z","roi":null,"last_updated":"2022-05-11T07:01:41.771Z"},{"id":"compound-usdt","symbol":"cusdt","name":"cUSDT","image":"https://assets.coingecko.com/coins/images/11621/large/cUSDT.png?1592113270","current_price":0.0217684,"market_cap":764342836,"market_cap_rank":90,"fully_diluted_valuation":null,"total_volume":8620.74,"high_24h":0.0217684,"low_24h":0.0217684,"price_change_24h":0.0,"price_change_percentage_24h":0.0,"market_cap_change_24h":6642701,"market_cap_change_percentage_24h":0.87669,"circulating_supply":35112487733.2372,"total_supply":35112487733.2372,"max_supply":null,"ath":0.02342332,"ath_change_percentage":-7.06526,"ath_date":"2021-05-19T15:22:06.410Z","atl":0.0102836,"atl_change_percentage":111.68084,"atl_date":"2020-07-04T17:59:08.922Z","roi":null,"last_updated":"2022-05-11T07:02:25.003Z"},{"id":"kusama","symbol":"ksm","name":"Kusama","image":"https://assets.coingecko.com/coins/images/9568/large/m4zRhP5e_400x400.jpg?1576190080","current_price":84.88,"market_cap":763880974,"market_cap_rank":89,"fully_diluted_valuation":850637674,"total_volume":110205558,"high_24h":103.83,"low_24h":85.06,"price_change_24h":-16.993859039505395,"price_change_percentage_24h":-16.682,"market_cap_change_24h":-151806226.2254846,"market_cap_change_percentage_24h":-16.57839,"circulating_supply":8980098.074112339,"total_supply":10000000.0,"max_supply":10000000.0,"ath":621.71,"ath_change_percentage":-86.31767,"ath_date":"2021-05-18T05:04:41.858Z","atl":0.876572,"atl_change_percentage":9604.13561,"atl_date":"2020-01-14T19:20:20.768Z","roi":null,"last_updated":"2022-05-11T07:02:00.207Z"},{"id":"gala","symbol":"gala","name":"Gala","image":"https://assets.coingecko.com/coins/images/12493/large/GALA-COINGECKO.png?1600233435","current_price":0.098122,"market_cap":740081174,"market_cap_rank":91,"fully_diluted_valuation":4906075637,"total_volume":479365567,"high_24h":0.121693,"low_24h":0.098095,"price_change_24h":-0.022397651292786046,"price_change_percentage_24h":-18.58431,"market_cap_change_24h":-172140986.92055452,"market_cap_change_percentage_24h":-18.87051,"circulating_supply":7542496572.319239,"total_supply":37428655600.2821,"max_supply":50000000000.0,"ath":0.824837,"ath_change_percentage":-88.10413,"ath_date":"2021-11-26T01:03:48.731Z","atl":0.00013475,"atl_change_percentage":72717.81184,"atl_date":"2020-12-28T08:46:48.367Z","roi":null,"last_updated":"2022-05-11T07:01:57.479Z"},{"id":"dash","symbol":"dash","name":"Dash","image":"https://assets.coingecko.com/coins/images/19/large/dash-logo.png?1548385930","current_price":68.09,"market_cap":729813088,"market_cap_rank":92,"fully_diluted_valuation":null,"total_volume":238533680,"high_24h":78.7,"low_24h":68.22,"price_change_24h":-9.609636077753493,"price_change_percentage_24h":-12.3678,"market_cap_change_24h":-103097064.09961867,"market_cap_change_percentage_24h":-12.37793,"circulating_supply":10718484.1205521,"total_supply":18920000.0,"max_supply":null,"ath":1493.59,"ath_change_percentage":-95.43273,"ath_date":"2017-12-20T00:00:00.000Z","atl":0.213899,"atl_change_percentage":31791.86104,"atl_date":"2014-02-14T00:00:00.000Z","roi":null,"last_updated":"2022-05-11T07:00:37.879Z"},{"id":"curve-dao-token","symbol":"crv","name":"Curve DAO Token","image":"https://assets.coingecko.com/coins/images/12124/large/Curve.png?1597369484","current_price":1.84,"market_cap":722286990,"market_cap_rank":93,"fully_diluted_valuation":6086711349,"total_volume":272927306,"high_24h":2.13,"low_24h":1.86,"price_change_24h":-0.27758785905165984,"price_change_percentage_24h":-13.10892,"market_cap_change_24h":-108886028.26852655,"market_cap_change_percentage_24h":-13.10028,"circulating_supply":391958099.3931446,"total_supply":1743505305.86926,"max_supply":3303030299.0,"ath":54.01,"ath_change_percentage":-96.58786,"ath_date":"2020-08-14T04:53:44.010Z","atl":0.331577,"atl_change_percentage":455.75743,"atl_date":"2020-11-05T13:09:50.181Z","roi":null,"last_updated":"2022-05-11T07:02:54.578Z"},{"id":"xdce-crowd-sale","symbol":"xdc","name":"XDC Network","image":"https://assets.coingecko.com/coins/images/2912/large/xdc-icon.png?1633700890","current_price":0.057853,"market_cap":708016096,"market_cap_rank":97,"fully_diluted_valuation":null,"total_volume":12726310,"high_24h":0.059483,"low_24h":0.057565,"price_change_24h":-0.000494670538423864,"price_change_percentage_24h":-0.84779,"market_cap_change_24h":-7978012.429635763,"market_cap_change_percentage_24h":-1.11426,"circulating_supply":12238141964.0,"total_supply":37599520715.0,"max_supply":null,"ath":0.192754,"ath_change_percentage":-69.9915,"ath_date":"2021-08-21T04:39:48.324Z","atl":0.00039532,"atl_change_percentage":14531.92006,"atl_date":"2019-07-22T00:00:00.000Z","roi":{"times":2.339355132952202,"currency":"eth","percentage":233.9355132952202},"last_updated":"2022-05-11T07:01:28.741Z"},{"id":"chiliz","symbol":"chz","name":"Chiliz","image":"https://assets.coingecko.com/coins/images/8834/large/Chiliz.png?1561970540","current_price":0.13215,"market_cap":705939580,"market_cap_rank":95,"fully_diluted_valuation":1174203341,"total_volume":160341011,"high_24h":0.154602,"low_24h":0.132098,"price_change_24h":-0.019437354016024894,"price_change_percentage_24h":-12.82254,"market_cap_change_24h":-103666545.6101085,"market_cap_change_percentage_24h":-12.80457,"circulating_supply":5344064580.0,"total_supply":8888888888.0,"max_supply":8888888888.0,"ath":0.878633,"ath_change_percentage":-84.96553,"ath_date":"2021-03-13T08:04:21.200Z","atl":0.00410887,"atl_change_percentage":3114.9406,"atl_date":"2019-09-28T00:00:00.000Z","roi":{"times":5.00682241608225,"currency":"usd","percentage":500.682241608225},"last_updated":"2022-05-11T07:02:31.952Z"},{"id":"enjincoin","symbol":"enj","name":"Enjin Coin","image":"https://assets.coingecko.com/coins/images/1102/large/enjin-coin-logo.png?1547035078","current_price":0.752202,"market_cap":705254487,"market_cap_rank":96,"fully_diluted_valuation":754815152,"total_volume":255988670,"high_24h":0.900171,"low_24h":0.754815,"price_change_24h":-0.11777452987139425,"price_change_percentage_24h":-13.53766,"market_cap_change_24h":-107898719.66168833,"market_cap_change_percentage_24h":-13.26917,"circulating_supply":934340659.567558,"total_supply":1000000000.0,"max_supply":1000000000.0,"ath":4.82,"ath_change_percentage":-84.37347,"ath_date":"2021-11-25T09:53:41.955Z","atl":0.01865964,"atl_change_percentage":3935.9528,"atl_date":"2017-11-12T00:00:00.000Z","roi":null,"last_updated":"2022-05-11T07:02:39.475Z"},{"id":"maiar-dex","symbol":"mex","name":"Maiar DEX","image":"https://assets.coingecko.com/coins/images/20657/large/MEX-icon.png?1637540149","current_price":0.00013907,"market_cap":698966004,"market_cap_rank":98,"fully_diluted_valuation":1125003161,"total_volume":625810,"high_24h":0.00015546,"low_24h":0.00013982,"price_change_24h":-1.6389925610201e-05,"price_change_percentage_24h":-10.54261,"market_cap_change_24h":-81798838.29020011,"market_cap_change_percentage_24h":-10.47676,"circulating_supply":4998941110102.0,"total_supply":8045920000000.0,"max_supply":8045920000000.0,"ath":0.00100138,"ath_change_percentage":-85.87056,"ath_date":"2021-12-02T02:08:57.932Z","atl":0.00013996,"atl_change_percentage":1.09347,"atl_date":"2022-05-10T03:34:28.367Z","roi":null,"last_updated":"2022-05-11T06:57:32.908Z"},{"id":"blockstack","symbol":"stx","name":"Stacks","image":"https://assets.coingecko.com/coins/images/2069/large/Stacks_logo_full.png?1604112510","current_price":0.661754,"market_cap":696706694,"market_cap_rank":94,"fully_diluted_valuation":null,"total_volume":24155143,"high_24h":0.742206,"low_24h":0.661915,"price_change_24h":-0.04776529727818635,"price_change_percentage_24h":-6.73206,"market_cap_change_24h":-52316583.94873643,"market_cap_change_percentage_24h":-6.98464,"circulating_supply":1052561461.68777,"total_supply":1352464600.0,"max_supply":null,"ath":3.39,"ath_change_percentage":-80.47237,"ath_date":"2021-12-01T01:32:34.725Z","atl":0.04559639,"atl_change_percentage":1351.68382,"atl_date":"2020-03-13T02:29:26.415Z","roi":{"times":4.514619096397401,"currency":"usd","percentage":451.4619096397401},"last_updated":"2022-05-11T07:01:50.829Z"},{"id":"harmony","symbol":"one","name":"Harmony","image":"https://assets.coingecko.com/coins/images/4344/large/Y88JAze.png?1565065793","current_price":0.056603,"market_cap":683227291,"market_cap_rank":99,"fully_diluted_valuation":745348537,"total_volume":111184260,"high_24h":0.069643,"low_24h":0.056654,"price_change_24h":-0.011189220559380252,"price_change_percentage_24h":-16.50508,"market_cap_change_24h":-135523093.5297445,"market_cap_change_percentage_24h":-16.55243,"circulating_supply":12059551243.1007,"total_supply":13156044839.793139,"max_supply":13156044839.793139,"ath":0.37902,"ath_change_percentage":-85.0524,"ath_date":"2021-10-26T09:28:49.782Z","atl":0.00127355,"atl_change_percentage":4348.53842,"atl_date":"2020-03-13T02:24:14.005Z","roi":{"times":16.82783595585243,"currency":"usd","percentage":1682.783595585243},"last_updated":"2022-05-11T07:01:56.345Z"},{"id":"basic-attention-token","symbol":"bat","name":"Basic Attention Token","image":"https://assets.coingecko.com/coins/images/677/large/basic-attention-token.png?1547034427","current_price":0.443232,"market_cap":664565666,"market_cap_rank":100,"fully_diluted_valuation":665436836,"total_volume":103611919,"high_24h":0.508933,"low_24h":0.443625,"price_change_24h":-0.05091087057655669,"price_change_percentage_24h":-10.30285,"market_cap_change_24h":-76107238.56354046,"market_cap_change_percentage_24h":-10.27542,"circulating_supply":1498036245.8773506,"total_supply":1500000000.0,"max_supply":1500000000.0,"ath":1.9,"ath_change_percentage":-76.65817,"ath_date":"2021-11-28T00:23:51.354Z","atl":0.072394,"atl_change_percentage":512.79353,"atl_date":"2017-07-16T00:00:00.000Z","roi":{"times":0.23130139030492225,"currency":"eth","percentage":23.130139030492224},"last_updated":"2022-05-11T07:01:55.330Z"}]